zap_ai/__init__.py
zap_ai/exceptions.py
zap_ai/utils.py
zap_ai/activities/__init__.py
zap_ai/activities/inference.py
zap_ai/activities/tool_execution.py
zap_ai/conversation/__init__.py
zap_ai/conversation/models.py
zap_ai/conversation/parser.py
zap_ai/core/__init__.py
zap_ai/core/agent.py
zap_ai/core/task.py
zap_ai/core/types.py
zap_ai/core/validation.py
zap_ai/core/zap.py
zap_ai/llm/__init__.py
zap_ai/llm/message_types.py
zap_ai/llm/provider.py
zap_ai/mcp/__init__.py
zap_ai/mcp/client_manager.py
zap_ai/mcp/schema_converter.py
zap_ai/mcp/tool_registry.py
zap_ai/tracing/__init__.py
zap_ai/tracing/base.py
zap_ai/tracing/langfuse_provider.py
zap_ai/tracing/noop_provider.py
zap_ai/tracing/protocol.py
zap_ai/worker/__init__.py
zap_ai/worker/__main__.py
zap_ai/worker/worker.py
zap_ai/workflows/__init__.py
zap_ai/workflows/agent_workflow.py
zap_ai/workflows/models.py
zap_ai-0.3.1.dist-info/METADATA
zap_ai-0.3.1.dist-info/WHEEL
zap_ai-0.3.1.dist-info/RECORD
