Metadata-Version: 2.4
Name: zap-ai
Version: 0.3.1
Summary: Zach's Agent Platform is a library built on top of Temporal, FastMCP, and LiteLLM to build resilient agents.
Author-email: Zach Cloud <me@zachb.cloud>
License: MIT
Classifier: License :: OSI Approved :: MIT License
Classifier: Operating System :: OS Independent
Classifier: Programming Language :: Python :: 3
Classifier: Programming Language :: Python :: 3.11
Classifier: Programming Language :: Python :: 3.12
Classifier: Programming Language :: Python :: 3.13
Requires-Python: >=3.11
Requires-Dist: fastmcp>=2.14.1
Requires-Dist: litellm>=1.50.0
Requires-Dist: pydantic>=2.0.0
Requires-Dist: python-dotenv>=1.2.1
Requires-Dist: temporalio>=1.10.0
Requires-Dist: typing-extensions>=4.4.0
Provides-Extra: langfuse
Requires-Dist: langfuse>=2.0.0; extra == 'langfuse'
